Metadata-Version: 1.0
Name: spoilerfy
Version: 1.1
Summary: Format your code for /r/dailyprogrammer
Home-page: https://www.github.com/rodenmonte/spoilerfy
Author: Monte Roden
Author-email: rodenmonte@gmail.com
License: MIT
Platform: UNKNOWN
